{
    "type": "Feature",
    "stac_version": "1.0.0-beta.2",
    "id": "Pakistan_1811336",
    "properties": {
        "country": "Pakistan",
        "chip_id": "1811336",
        "datetime": "2017-06-28T00:00:00Z"
    },
    "geometry": {
        "type": "Polygon",
        "coordinates": [
            [
                [
                    71.29030094772524,
                    32.19561978284365
                ],
                [
                    71.29030094772524,
                    32.24161352539057
                ],
                [
                    71.24430720517832,
                    32.24161352539057
                ],
                [
                    71.24430720517832,
                    32.19561978284365
                ],
                [
                    71.29030094772524,
                    32.19561978284365
                ]
            ]
        ]
    },
    "links": [
        {
            "rel": "root",
            "href": "../../catalog.json",
            "type": "application/json"
        },
        {
            "rel": "collection",
            "href": "../collection.json",
            "type": "application/json"
        },
        {
            "rel": "parent",
            "href": "../collection.json",
            "type": "application/json"
        }
    ],
    "assets": {
        "S1Weak": {
            "href": "https://storage.googleapis.com/sen1floods11/v1.1/data/flood_events/WeaklyLabeled/S1Weak/Pakistan_1811336_S1Weak.tif",
            "type": "image/tiff; application=geotiff",
            "title": "GeoTiff"
        }
    },
    "bbox": [
        71.24430720517832,
        32.19561978284365,
        71.29030094772524,
        32.24161352539057
    ],
    "collection": "sen1floods11_weak_labeled_source"
}