{
    "type": "Feature",
    "stac_version": "1.0.0-beta.2",
    "id": "Pakistan_9392758",
    "properties": {
        "country": "Pakistan",
        "chip_id": "9392758",
        "datetime": "2017-06-28T00:00:00Z"
    },
    "geometry": {
        "type": "Polygon",
        "coordinates": [
            [
                [
                    71.33629469027215,
                    32.3336010104844
                ],
                [
                    71.33629469027215,
                    32.37959475303133
                ],
                [
                    71.29030094772523,
                    32.37959475303133
                ],
                [
                    71.29030094772523,
                    32.3336010104844
                ],
                [
                    71.33629469027215,
                    32.3336010104844
                ]
            ]
        ]
    },
    "links": [
        {
            "rel": "root",
            "href": "../../catalog.json",
            "type": "application/json"
        },
        {
            "rel": "collection",
            "href": "../collection.json",
            "type": "application/json"
        },
        {
            "rel": "parent",
            "href": "../collection.json",
            "type": "application/json"
        }
    ],
    "assets": {
        "S1Weak": {
            "href": "https://storage.googleapis.com/sen1floods11/v1.1/data/flood_events/WeaklyLabeled/S1Weak/Pakistan_9392758_S1Weak.tif",
            "type": "image/tiff; application=geotiff",
            "title": "GeoTiff"
        }
    },
    "bbox": [
        71.29030094772523,
        32.3336010104844,
        71.33629469027215,
        32.37959475303133
    ],
    "collection": "sen1floods11_weak_labeled_source"
}